majortomo/__init__.py
majortomo/broker.py
majortomo/client.py
majortomo/config.py
majortomo/echo.py
majortomo/error.py
majortomo/mock.py
majortomo/protocol.py
majortomo/py.typed
majortomo/util.py
majortomo/worker.py
majortomo-0.2.0.dist-info/LICENSE
majortomo-0.2.0.dist-info/METADATA
majortomo-0.2.0.dist-info/WHEEL
majortomo-0.2.0.dist-info/top_level.txt
majortomo-0.2.0.dist-info/RECORD
