Metadata-Version: 2.1
Name: majortomo
Version: 0.2.0
Summary: Majortomo - ZMQ MDP 0.2 (Majordomo) Python Implementation
Home-page: https://github.com/shoppimon/majortomo
Author: Shahar Evron
Author-email: shahar@shoppimon.com
License: Apache 2.0
Platform: UNKNOWN
Requires-Python: >=3.6.0
Requires-Dist: figcan
Requires-Dist: pyyaml
Requires-Dist: pyzmq
